README.md
setup.py
seki/__init__.py
seki/__main__.py
seki/__version__.py
seki/cli.py
seki/conf.py
seki.egg-info/PKG-INFO
seki.egg-info/SOURCES.txt
seki.egg-info/dependency_links.txt
seki.egg-info/entry_points.txt
seki.egg-info/requires.txt
seki.egg-info/top_level.txt
seki/commands/__init__.py
seki/commands/build.py
seki/commands/cron.py
seki/commands/drone.py
seki/commands/repo.py
seki/commands/run.py
seki/commands/shared.py
seki/commands/template.py
seki/utils/__init__.py
seki/utils/drone.py
seki/utils/encodings.py
seki/utils/git_cli.py